fastpgcache/__init__.py
fastpgcache/admin.py
fastpgcache/client.py
fastpgcache/token_provider.py
fastpgcache-0.1.3.dist-info/licenses/LICENSE
fastpgcache-0.1.3.dist-info/METADATA
fastpgcache-0.1.3.dist-info/WHEEL
fastpgcache-0.1.3.dist-info/entry_points.txt
fastpgcache-0.1.3.dist-info/top_level.txt
fastpgcache-0.1.3.dist-info/RECORD
